grad_cache_con_learning/__init__.py
grad_cache_con_learning/context_managers.py
grad_cache_con_learning/grad_cache.py
grad_cache_con_learning/losses.py
grad_cache_con_learning-1.0.2.dist-info/LICENSE
grad_cache_con_learning-1.0.2.dist-info/METADATA
grad_cache_con_learning-1.0.2.dist-info/WHEEL
grad_cache_con_learning-1.0.2.dist-info/top_level.txt
grad_cache_con_learning-1.0.2.dist-info/RECORD
