Metadata-Version: 2.1
Name: grad_cache_con_learning
Version: 1.0.2
Home-page: https://github.com/delyan-boychev/grad-cache-con-learning
Author: Delyan Boychev
Author-email: delyan.boychev05@gmail.com
License: Apache-2.0
License-File: LICENSE
